radsim/__init__.py
radsim/_version.py
radsim/digest.py
radsim/main.py
radsim/utils.py
radsim-0.1.2.dist-info/METADATA
radsim-0.1.2.dist-info/WHEEL
radsim-0.1.2.dist-info/entry_points.txt
radsim-0.1.2.dist-info/top_level.txt
radsim-0.1.2.dist-info/RECORD
