Metadata-Version: 2.1
Name: radsim
Version: 0.1.2
Summary: RADsim: simulate reduced-represention sequencing platforms based on restriction digestion, including RADseq and GBS. 
Home-page: https://github.com/kdmurray91/radhax
Author: Kevin Murray
Author-email: spam@kdmurray.id.au
License: UNKNOWN
Keywords: bioinformatics,RADseq,GBS,Genotyping by Sequencing,Next-gen Sequencing
Platform: UNKNOWN
Classifier: Programming Language :: Python
Classifier: Programming Language :: Python :: 2
Classifier: Programming Language :: Python :: 3
Classifier: Development Status :: 3 - Alpha
Classifier: Environment :: Console
Classifier: Intended Audience :: Developers
Classifier: Operating System :: OS Independent
Classifier: Topic :: Software Development :: Libraries :: Python Modules
Classifier: Topic :: Scientific/Engineering :: Bio-Informatics
Classifier: License :: OSI Approved :: GNU General Public License v3 or later (GPLv3+)
Requires-Dist: numpy
Requires-Dist: biopython
Requires-Dist: docopt
Requires-Dist: screed (>=0.9)
Requires-Dist: six
Requires-Dist: progressbar2
